python_xxl_job_helper-0.1.4.dist-info/licenses/LICENSE
xxl_job_helper/__init__.py
xxl_job_helper/client.py
xxl_job_helper/utils.py
python_xxl_job_helper-0.1.4.dist-info/METADATA
python_xxl_job_helper-0.1.4.dist-info/WHEEL
python_xxl_job_helper-0.1.4.dist-info/top_level.txt
python_xxl_job_helper-0.1.4.dist-info/RECORD
