Metadata-Version: 2.4
Name: python_xxl_job_helper
Version: 0.1.4
Summary: xxl job helper python package
Author-email: ckf10000 <ckf10000@sina.com>
License:                                  Apache License
Project-URL: Homepage, https://github.com/ckf10000/python-xxl-job-helper
Project-URL: Source, https://github.com/ckf10000/python-xxl-job-helper
Project-URL: Issues, https://github.com/ckf10000/python-xxl-job-helper/issues
Requires-Python: >=3.12
License-File: LICENSE
Requires-Dist: python_http_helper>=0.2.0; python_version >= "3.12"
Dynamic: license-file
